boto3_session/__init__.py
boto3_session/py.typed
boto3_session/session.py
boto3_session/version.py
boto3_session-0.0.9.dist-info/WHEEL
boto3_session-0.0.9.dist-info/METADATA
boto3_session-0.0.9.dist-info/RECORD
