Metadata-Version: 2.4
Name: boto3-session
Version: 0.0.9
Summary: Wrapper library for python boto3.session.Session.
Keywords: aws,boto3
Author: rcmdnk
Author-email: rcmdnk <rcmdnk@gmail.com>
License-Expression: Apache-2.0
Requires-Dist: boto3>=1.33
Requires-Dist: botocore>=1.33.2
Requires-Python: >=3.9
Project-URL: Documentation, https://github.com/rcmdnk/boto3-session
Project-URL: Homepage, https://github.com/rcmdnk/boto3-session
Project-URL: Issue, https://github.com/rcmdnk/boto3-session/ssues
Project-URL: Repository, https://github.com/rcmdnk/boto3-session
